hashcli/__init__.py
hashcli/command_proxy.py
hashcli/config.py
hashcli/history.py
hashcli/llm_handler.py
hashcli/main.py
hashcli/commands/__init__.py
hashcli/commands/_tldr.py
hashcli/commands/clear.py
hashcli/commands/config.py
hashcli/commands/fix.py
hashcli/commands/help.py
hashcli/commands/ls.py
hashcli/commands/model.py
hashcli/commands/tldr.py
hashcli/providers/__init__.py
hashcli/providers/anthropic_provider.py
hashcli/providers/base.py
hashcli/providers/google_provider.py
hashcli/providers/openai_provider.py
hashcli/shell/README.md
hashcli/shell/setup_shell_integration.sh
hashcli/shell/test_installation.sh
hashcli/shell/bash/hash.bash
hashcli/shell/bash/hash_completion.bash
hashcli/shell/bash/install.sh
hashcli/shell/bash/test.sh
hashcli/shell/fish/completions.fish
hashcli/shell/fish/hash.fish
hashcli/shell/fish/install.sh
hashcli/shell/fish/test.sh
hashcli/shell/powershell/completions.ps1
hashcli/shell/powershell/hash.ps1
hashcli/shell/powershell/install.ps1
hashcli/shell/powershell/uninstall.ps1
hashcli/shell/zsh/_hash
hashcli/shell/zsh/hash.zsh
hashcli/shell/zsh/install.sh
hashcli/shell/zsh/test.sh
hashcli/tools/__init__.py
hashcli/tools/base.py
hashcli/tools/code_analysis.py
hashcli/tools/filesystem.py
hashcli/tools/shell.py
hashcli/tools/web_search.py
hashcli-0.3.0.dist-info/licenses/LICENSE
hashcli-0.3.0.dist-info/METADATA
hashcli-0.3.0.dist-info/WHEEL
hashcli-0.3.0.dist-info/entry_points.txt
hashcli-0.3.0.dist-info/top_level.txt
hashcli-0.3.0.dist-info/RECORD
