Metadata-Version: 2.4
Name: hashcli
Version: 0.3.0
Summary: Hash - Intelligent CLI system with dual-mode functionality (LLM chat and command proxy)
Author: Wensheng Wang
License-Expression: MIT
Project-URL: Homepage, https://github.com/wensheng/hash
Project-URL: Repository, https://github.com/wensheng/hash.git
Project-URL: Documentation, https://github.com/wensheng/hash/docs
Project-URL: Bug Tracker, https://github.com/wensheng/hash/issues
Keywords: cli,llm,assistant,terminal,ai,hash
Classifier: Development Status :: 3 - Alpha
Classifier: Intended Audience :: Developers
Classifier: Programming Language :: Python :: 3
Classifier: Programming Language :: Python :: 3.11
Classifier: Programming Language :: Python :: 3.12
Classifier: Programming Language :: Python :: 3.13
Classifier: Topic :: Software Development :: Libraries :: Python Modules
Classifier: Topic :: System :: System Shells
Classifier: Topic :: Utilities
Requires-Python: >=3.10
License-File: LICENSE
Requires-Dist: openai>=1.0.0
Requires-Dist: anthropic>=0.28.0
Requires-Dist: typer[all]>=0.9.0
Requires-Dist: rich>=13.0.0
Requires-Dist: pydantic>=2.0.0
Requires-Dist: aiohttp>=3.8.0
Requires-Dist: toml>=0.10.2
Requires-Dist: google-genai<2.0.0,>=1.57.0
Requires-Dist: termcolor<4.0.0,>=3.3.0
Requires-Dist: colorama<0.5.0,>=0.4.6; sys_platform == "win32"
Requires-Dist: shtab<2.0.0,>=1.8.0
Provides-Extra: dev
Requires-Dist: pytest>=8.0.0; extra == "dev"
Requires-Dist: pytest-asyncio>=0.21.0; extra == "dev"
Requires-Dist: pytest-cov>=4.0.0; extra == "dev"
Requires-Dist: pytest-mock<4.0.0,>=3.15.1; extra == "dev"
Requires-Dist: black>=23.0.0; extra == "dev"
Requires-Dist: isort>=5.0.0; extra == "dev"
Requires-Dist: mypy>=1.0.0; extra == "dev"
Requires-Dist: flake8>=6.0.0; extra == "dev"
Requires-Dist: pre-commit>=3.0.0; extra == "dev"
Dynamic: license-file
